codes/JK_FF.v
module vlsi(input clk,rst,j,k,output reg q, output qbar);
always@(posedge clk or negedge rst)begin
	if(~rst)begin
		q <= 1'b0;
	end
	else begin
		case({j,k})
			2'b00: q <= q;
			2'b01: q <= 0;
			2'b10: q <= 1;
			2'b11: q <= ~q;
		endcase
	end
end
assign qbar = ~q;
endmodule
 

/*
module vlsi(input clk,rst,j,k,output reg q,output qbar);
always@(posedge clk or posedge rst)begin
	if(rst)begin
		q <= 1'b0;
	end
	else if(j == 0 && k == 0)begin
		q <= q;
	end
	else if(j == 0 && k == 1)begin
		q <= 1'b0;
	end
	else if(j == 1 && k == 0)begin
		q <= 1'b1;
	end
	else begin
		q <= ~q;
	end
end
assign qbar = ~q;
endmodule
*/

codes/jkTB.v
module Testbench;
reg clk,rst,j,k;
wire q,qbar;
vlsi v1(.clk(clk),.rst(rst),.j(j),.k(k),.q(q),.qbar(qbar));

initial clk = 0;
always begin 
#5 clk = ~clk;
end

initial begin
$dumpfile("vlsi.vcd");
$dumpvars(0,Testbench);
$monitor($time, " rst = %b,j = %b,k = %b, q = %b, qbar = %b",rst,j,k,q,qbar);

// Initialize
    rst = 0; j = 0; k = 0;
    
    // Release reset after 12 units (offset from clock edge)
    #12 rst = 1;

    // Hold state
    #10 j = 0; k = 0;

    // Set state (q should turn 1 on next posedge)
    #10 j = 1; k = 0;

    // Toggle state (q should toggle to 0, then 1)
    #10 j = 1; k = 1;
    #20; // Let it toggle over 2 clock cycles

    // Reset state
    #10 j = 0; k = 1;
    #10;

$display("end of simulation");
$finish;
end
endmodule

codes/vlsi.vcd
$date
	Tue Sep 22 22:58:30 2026
$end
$version
	Icarus Verilog
$end
$timescale
	1s
$end
$scope module Testbench $end
$var wire 1 ! qbar $end
$var wire 1 " q $end
$var reg 1 # clk $end
$var reg 1 $ j $end
$var reg 1 % k $end
$var reg 1 & rst $end
$scope module v1 $end
$var wire 1 # clk $end
$var wire 1 $ j $end
$var wire 1 % k $end
$var wire 1 ! qbar $end
$var wire 1 & rst $end
$var reg 1 " q $end
$upscope $end
$upscope $end
$enddefinitions $end
$comment Show the parameter values. $end
$dumpall
$end
#0
$dumpvars
0&
0%
0$
0#
0"
1!
$end
#5
1#
#10
0#
#12
1&
#15
1#
#20
0#
#25
1#
#30
0#
#32
1$
#35
0!
1"
1#
#40
0#
#42
1%
#45
1!
0"
1#
#50
0#
#55
0!
1"
1#
#60
0#
#65
1!
0"
1#
#70
0#
#72
0$
